aws_sfn_pydantic/__init__.py
aws_sfn_pydantic/api/__init__.py
aws_sfn_pydantic/api/define.py
aws_sfn_pydantic/api/sfn.py
aws_sfn_pydantic/generated/__init__.py
aws_sfn_pydantic/generated/base_state_machine.py
aws_sfn_pydantic/utils/__init__.py
aws_sfn_pydantic/utils/boto.py
aws_step_functions_pydantic-0.0.5.dist-info/METADATA
aws_step_functions_pydantic-0.0.5.dist-info/WHEEL
aws_step_functions_pydantic-0.0.5.dist-info/entry_points.txt
aws_step_functions_pydantic-0.0.5.dist-info/licenses/LICENSE
aws_step_functions_pydantic-0.0.5.dist-info/RECORD
