Metadata-Version: 2.1
Name: aws-step-functions-pydantic
Version: 0.0.5
Summary: Pydantic models for AWS step functions
Author-Email: Louis Maddox <louismmx@gmail.com>
Classifier: Development Status :: 4 - Beta
Classifier: Intended Audience :: Developers
Classifier: Natural Language :: English
Classifier: License :: OSI Approved :: MIT License
Classifier: Operating System :: OS Independent
Classifier: Programming Language :: Python
Classifier: Programming Language :: Python :: Implementation :: CPython
Classifier: Programming Language :: Python :: 3
Classifier: Programming Language :: Python :: 3.9
Classifier: Programming Language :: Python :: 3.10
Classifier: Programming Language :: Python :: 3.11
Classifier: Programming Language :: Python :: 3.12
Classifier: Programming Language :: Python :: 3.13
Requires-Python: >=3.9
Provides-Extra: dev
Requires-Dist: pdm>=2.22.3; extra == "dev"
Requires-Dist: pdm-bump>=0.9.10; extra == "dev"
Requires-Dist: pre-commit>=4.1.0; extra == "dev"
